matplotview/__init__.py
matplotview/_docs.py
matplotview/_transform_renderer.py
matplotview/_view_axes.py
matplotview-1.0.1.dist-info/LICENSE
matplotview-1.0.1.dist-info/METADATA
matplotview-1.0.1.dist-info/WHEEL
matplotview-1.0.1.dist-info/top_level.txt
matplotview-1.0.1.dist-info/RECORD
