Metadata-Version: 2.1
Name: matplotview
Version: 1.0.1
Summary: A library for creating lightweight views of matplotlib axes.
Home-page: https://github.com/matplotlib/matplotview
Author: Isaac Robinson
Author-email: isaac.k.robinson2000@gmail.com
License: PSF
Project-URL: Bug Tracker, https://github.com/matplotlib/matplotview/issues
Platform: any
Classifier: Development Status :: 3 - Alpha
Classifier: Framework :: Matplotlib
Classifier: License :: OSI Approved :: Python Software Foundation License
Classifier: Programming Language :: Python
Classifier: Programming Language :: Python :: 3
Classifier: Programming Language :: Python :: 3.7
Classifier: Programming Language :: Python :: 3.8
Classifier: Programming Language :: Python :: 3.9
Classifier: Programming Language :: Python :: 3.10
Classifier: Topic :: Scientific/Engineering :: Visualization
Classifier: Operating System :: OS Independent
Requires-Python: >=3.7
License-File: LICENSE
Requires-Dist: matplotlib >=3.5.1
Requires-Dist: numpy
